[
  {
    "ticker": "FNKO",
    "sector": "Consumer Non-Durables",
    "mktcap": "Medium",
    "bb_window": 3,
    "bb_std": 0.1,
    "peers": "$GPC $POOL $LKQ $SPY",
    "ror": 82.99,
    "entry_frequency": 113,
    "time_period": "day"
  },
  {
    "ticker": "HOV",
    "sector": "Capital Goods",
    "mktcap": "Medium",
    "bb_window": 3,
    "bb_std": 0.1,
    "peers": "$DHI $LEN $NVR $SPY",
    "ror": 82.87,
    "entry_frequency": 113,
    "time_period": "day"
  },
  {
    "ticker": "TGLS",
    "sector": "Consumer Durables",
    "mktcap": "Medium",
    "bb_window": 3,
    "bb_std": 0.1,
    "peers": "$GRUPOARGOS.BC $CEMARGOS.BC $TITAN.BC $SPY",
    "ror": 71.99,
    "entry_frequency": 98,
    "time_period": "day"
  },
  {
    "ticker": "ZEUS",
    "sector": "Basic Industries",
    "mktcap": "Medium",
    "bb_window": 3,
    "bb_std": 0.1,
    "peers": "$NUE $STLD $RS $SPY",
    "ror": 71.92,
    "entry_frequency": 98,
    "time_period": "day"
  },
  {
    "ticker": "RCKY",
    "sector": "Consumer Non-Durables",
    "mktcap": "Medium",
    "bb_window": 3,
    "bb_std": 0.1,
    "peers": "$NKE $DECK $SKX $SPY",
    "ror": 53.27,
    "entry_frequency": 73,
    "time_period": "day"
  },
  {
    "ticker": "CLMT",
    "sector": "Energy",
    "mktcap": "Medium",
    "bb_window": 3,
    "bb_std": 0.1,
    "peers": "$PSX $MPC $VLO $SPY",
    "ror": 50.25,
    "entry_frequency": 69,
    "time_period": "day"
  },
  {
    "ticker": "DAC",
    "sector": "Transportation",
    "mktcap": "Medium",
    "bb_window": 3,
    "bb_std": 0.1,
    "peers": "$SBLK $DAC $DSX $SPY",
    "ror": 45.99,
    "entry_frequency": 63,
    "time_period": "day"
  },
  {
    "ticker": "DBI",
    "sector": "Consumer Services",
    "mktcap": "Medium",
    "bb_window": 3,
    "bb_std": 0.1,
    "peers": "$TJX $ROST $BURL $SPY",
    "ror": 44.45,
    "entry_frequency": 61,
    "time_period": "day"
  },
  {
    "ticker": "OMP",
    "sector": "Energy",
    "mktcap": "Medium",
    "bb_window": 3,
    "bb_std": 0.1,
    "peers": "$EPD $KMI $WMB $SPY",
    "ror": 41.57,
    "entry_frequency": 57,
    "time_period": "day"
  },
  {
    "ticker": "BW",
    "sector": "Capital Goods",
    "mktcap": "Medium",
    "bb_window": 3,
    "bb_std": 0.1,
    "peers": "$BE $TPIC $AZZ $SPY",
    "ror": 39.34,
    "entry_frequency": 54,
    "time_period": "day"
  },
  {
    "ticker": "CAL",
    "sector": "Consumer Non-Durables",
    "mktcap": "Medium",
    "bb_window": 3,
    "bb_std": 0.1,
    "peers": "$TJX $ROST $BURL $SPY",
    "ror": 33.68,
    "entry_frequency": 46,
    "time_period": "day"
  },
  {
    "ticker": "HCI",
    "sector": "Finance",
    "mktcap": "Medium",
    "bb_window": 3,
    "bb_std": 0.1,
    "peers": "$PGR $TRV $ALL $SPY",
    "ror": 31.24,
    "entry_frequency": 43,
    "time_period": "day"
  },
  {
    "ticker": "AMTBB",
    "sector": "Finance",
    "mktcap": "Medium",
    "bb_window": 3,
    "bb_std": 0.1,
    "peers": "$TFC $PNC $FRC $SPY",
    "ror": 30.81,
    "entry_frequency": 43,
    "time_period": "day"
  },
  {
    "ticker": "RBNC",
    "sector": "Finance",
    "mktcap": "Medium",
    "bb_window": 3,
    "bb_std": 0.1,
    "peers": "$TFC $PNC $FRC $SPY",
    "ror": 30.77,
    "entry_frequency": 43,
    "time_period": "day"
  },
  {
    "ticker": "MX",
    "sector": "Technology",
    "mktcap": "Medium",
    "bb_window": 3,
    "bb_std": 0.1,
    "peers": "$MX $SPY",
    "ror": 30.58,
    "entry_frequency": 42,
    "time_period": "day"
  },
  {
    "ticker": "CPF",
    "sector": "Finance",
    "mktcap": "Medium",
    "bb_window": 3,
    "bb_std": 0.1,
    "peers": "$TFC $PNC $FRC $SPY",
    "ror": 28.15,
    "entry_frequency": 39,
    "time_period": "day"
  },
  {
    "ticker": "SCVL",
    "sector": "Consumer Services",
    "mktcap": "Medium",
    "bb_window": 3,
    "bb_std": 0.1,
    "peers": "$TJX $ROST $BURL $SPY",
    "ror": 27.38,
    "entry_frequency": 38,
    "time_period": "day"
  },
  {
    "ticker": "FMBH",
    "sector": "Finance",
    "mktcap": "Medium",
    "bb_window": 3,
    "bb_std": 0.1,
    "peers": "$TFC $PNC $FRC $SPY",
    "ror": 27.06,
    "entry_frequency": 38,
    "time_period": "day"
  },
  {
    "ticker": "GPX",
    "sector": "Consumer Services",
    "mktcap": "Medium",
    "bb_window": 3,
    "bb_std": 0.1,
    "peers": "$RHI $UPWK $MAN $SPY",
    "ror": 24.91,
    "entry_frequency": 35,
    "time_period": "day"
  },
  {
    "ticker": "ALTG",
    "sector": "Capital Goods",
    "mktcap": "Medium",
    "bb_window": 3,
    "bb_std": 0.1,
    "peers": "$FAST $URI $GWW $SPY",
    "ror": 24.78,
    "entry_frequency": 34,
    "time_period": "day"
  },
  {
    "ticker": "IMKTA",
    "sector": "Consumer Services",
    "mktcap": "Medium",
    "bb_window": 3,
    "bb_std": 0.1,
    "peers": "$KR $ACI $CASY $SPY",
    "ror": 23.78,
    "entry_frequency": 33,
    "time_period": "day"
  },
  {
    "ticker": "CIVB",
    "sector": "Finance",
    "mktcap": "Medium",
    "bb_window": 2,
    "bb_std": 0.1,
    "peers": "$TFC $PNC $FRC $SPY",
    "ror": 20.95,
    "entry_frequency": 29,
    "time_period": "day"
  },
  {
    "ticker": "CUBI",
    "sector": "Finance",
    "mktcap": "Medium",
    "bb_window": 3,
    "bb_std": 0.1,
    "peers": "$TFC $PNC $FRC $SPY",
    "ror": 20.35,
    "entry_frequency": 28,
    "time_period": "day"
  },
  {
    "ticker": "UMH",
    "sector": "Consumer Services",
    "mktcap": "Medium",
    "bb_window": 3,
    "bb_std": 0.1,
    "peers": "$EQR $AVB $INVH $SPY",
    "ror": 20.27,
    "entry_frequency": 28,
    "time_period": "day"
  },
  {
    "ticker": "AGM",
    "sector": "Finance",
    "mktcap": "Medium",
    "bb_window": 3,
    "bb_std": 0.1,
    "peers": "$RKT $PCSO $UWMC $SPY",
    "ror": 20.27,
    "entry_frequency": 28,
    "time_period": "day"
  },
  {
    "ticker": "PGC",
    "sector": "Finance",
    "mktcap": "Medium",
    "bb_window": 3,
    "bb_std": 0.1,
    "peers": "$TFC $PNC $FRC $SPY",
    "ror": 19.78,
    "entry_frequency": 28,
    "time_period": "day"
  },
  {
    "ticker": "NFBK",
    "sector": "Finance",
    "mktcap": "Medium",
    "bb_window": 3,
    "bb_std": 0.1,
    "peers": "$RKT $PCSO $UWMC $SPY",
    "ror": 19.32,
    "entry_frequency": 27,
    "time_period": "day"
  },
  {
    "ticker": "DLTH",
    "sector": "Consumer Services",
    "mktcap": "Medium",
    "bb_window": 3,
    "bb_std": 0.1,
    "peers": "$AMZN $BKNG $DASH $SPY",
    "ror": 19.0,
    "entry_frequency": 27,
    "time_period": "day"
  },
  {
    "ticker": "USX",
    "sector": "Transportation",
    "mktcap": "Medium",
    "bb_window": 3,
    "bb_std": 0.1,
    "peers": "$UBER $ODFL $LYFT $SPY",
    "ror": 17.81,
    "entry_frequency": 25,
    "time_period": "day"
  },
  {
    "ticker": "PBFX",
    "sector": "Energy",
    "mktcap": "Medium",
    "bb_window": 3,
    "bb_std": 0.1,
    "peers": "$EPD $KMI $WMB $SPY",
    "ror": 17.73,
    "entry_frequency": 25,
    "time_period": "day"
  },
  {
    "ticker": "VBTX",
    "sector": "Finance",
    "mktcap": "Medium",
    "bb_window": 3,
    "bb_std": 0.1,
    "peers": "$TFC $PNC $FRC $SPY",
    "ror": 16.46,
    "entry_frequency": 23,
    "time_period": "day"
  },
  {
    "ticker": "AMEH",
    "sector": "Consumer Services",
    "mktcap": "Medium",
    "bb_window": 3,
    "bb_std": 0.1,
    "peers": "$CVS $CI $LH $SPY",
    "ror": 15.49,
    "entry_frequency": 22,
    "time_period": "day"
  },
  {
    "ticker": "QCRH",
    "sector": "Finance",
    "mktcap": "Medium",
    "bb_window": 3,
    "bb_std": 0.1,
    "peers": "$TFC $PNC $FRC $SPY",
    "ror": 14.75,
    "entry_frequency": 21,
    "time_period": "day"
  },
  {
    "ticker": "DIN",
    "sector": "Consumer Services",
    "mktcap": "Medium",
    "bb_window": 3,
    "bb_std": 0.1,
    "peers": "$MCD $SBUX $CMG $SPY",
    "ror": 14.48,
    "entry_frequency": 21,
    "time_period": "day"
  },
  {
    "ticker": "PLYM",
    "sector": "Consumer Services",
    "mktcap": "Medium",
    "bb_window": 3,
    "bb_std": 0.1,
    "peers": "$PLD $DRE $COLD $SPY",
    "ror": 14.43,
    "entry_frequency": 20,
    "time_period": "day"
  },
  {
    "ticker": "BBCP",
    "sector": "Basic Industries",
    "mktcap": "Medium",
    "bb_window": 3,
    "bb_std": 0.1,
    "peers": "$PWR $ACM $MTZ $SPY",
    "ror": 13.78,
    "entry_frequency": 20,
    "time_period": "day"
  },
  {
    "ticker": "NSSC",
    "sector": "Capital Goods",
    "mktcap": "Medium",
    "bb_window": 3,
    "bb_std": 0.1,
    "peers": "$KEYS $ZBRA $TRMB $SPY",
    "ror": 13.73,
    "entry_frequency": 20,
    "time_period": "day"
  },
  {
    "ticker": "MLR",
    "sector": "Capital Goods",
    "mktcap": "Medium",
    "bb_window": 3,
    "bb_std": 0.1,
    "peers": "$CAT $CMI $PCAR $SPY",
    "ror": 12.95,
    "entry_frequency": 18,
    "time_period": "day"
  },
  {
    "ticker": "NCBS",
    "sector": "Finance",
    "mktcap": "Medium",
    "bb_window": 3,
    "bb_std": 0.1,
    "peers": "$TFC $PNC $FRC $SPY",
    "ror": 12.87,
    "entry_frequency": 18,
    "time_period": "day"
  },
  {
    "ticker": "TGH",
    "sector": "Technology",
    "mktcap": "Medium",
    "bb_window": 3,
    "bb_std": 0.1,
    "peers": "$TRTN $TGH $SPY",
    "ror": 11.05,
    "entry_frequency": 16,
    "time_period": "day"
  },
  {
    "ticker": "AEGN",
    "sector": "Basic Industries",
    "mktcap": "Medium",
    "bb_window": 2,
    "bb_std": 0.8,
    "peers": "$PWR $ACM $MTZ $SPY",
    "ror": 9.81,
    "entry_frequency": 14,
    "time_period": "day"
  },
  {
    "ticker": "TPCO",
    "sector": "Consumer Services",
    "mktcap": "Medium",
    "bb_window": 2,
    "bb_std": 0.8,
    "peers": "$NWSA $NYT $JW.A $SPY",
    "ror": 7.59,
    "entry_frequency": 11,
    "time_period": "day"
  },
  {
    "ticker": "CATC",
    "sector": "Finance",
    "mktcap": "Medium",
    "bb_window": 3,
    "bb_std": 1.0,
    "peers": "$TFC $PNC $FRC $SPY",
    "ror": 6.6,
    "entry_frequency": 10,
    "time_period": "day"
  },
  {
    "ticker": "ORC",
    "sector": "Consumer Services",
    "mktcap": "Medium",
    "bb_window": 3,
    "bb_std": 0.4,
    "peers": "$NLY $AGNC $STWD $SPY",
    "ror": 5.62,
    "entry_frequency": 9,
    "time_period": "day"
  },
  {
    "ticker": "ICAD",
    "sector": "Health Care",
    "mktcap": "Medium",
    "bb_window": 5,
    "bb_std": 1.0,
    "peers": "$VEEV $TDOC $CERN $SPY",
    "ror": 5.53,
    "entry_frequency": 8,
    "time_period": "day"
  },
  {
    "ticker": "ARR",
    "sector": "Consumer Services",
    "mktcap": "Medium",
    "bb_window": 5,
    "bb_std": 1.0,
    "peers": "$NLY $AGNC $STWD $SPY",
    "ror": 3.62,
    "entry_frequency": 6,
    "time_period": "day"
  }
]