[
  {
    "ticker": "PIRS",
    "sector": "Health Care",
    "mktcap": "Small",
    "bb_window": null,
    "bb_std": null,
    "peers": "$950160.KQ $ABBV $AMGN $SPY",
    "ror": 22.38,
    "entry_frequency": 23,
    "200sma_double_agent": 2
  },
  {
    "ticker": "GLG",
    "sector": "Finance",
    "mktcap": "Small",
    "bb_window": null,
    "bb_std": null,
    "peers": "$600662.SS $699.HK $600611.SS $SPY",
    "ror": 20.23,
    "entry_frequency": 21,
    "200sma_double_agent": 2
  },
  {
    "ticker": "GLYC",
    "sector": "Health Care",
    "mktcap": "Small",
    "bb_window": null,
    "bb_std": null,
    "peers": "$950160.KQ $ABBV $AMGN $SPY",
    "ror": 18.58,
    "entry_frequency": 20,
    "200sma_double_agent": 2
  },
  {
    "ticker": "CYRN",
    "sector": "Technology",
    "mktcap": "Small",
    "bb_window": null,
    "bb_std": null,
    "peers": "$CHKP $CYBR $ALLT $SPY",
    "ror": 16.01,
    "entry_frequency": 17,
    "200sma_double_agent": 2
  },
  {
    "ticker": "CTK",
    "sector": "Technology",
    "mktcap": "Small",
    "bb_window": null,
    "bb_std": null,
    "peers": "$688111.SS $600588.SS $002230.SZ $SPY",
    "ror": 13.41,
    "entry_frequency": 14,
    "200sma_double_agent": 2
  },
  {
    "ticker": "PROG",
    "sector": "Health Care",
    "mktcap": "Small",
    "bb_window": null,
    "bb_std": null,
    "peers": "$CVS $CI $LH $SPY",
    "ror": 12.35,
    "entry_frequency": 13,
    "200sma_double_agent": 2
  },
  {
    "ticker": "AAU",
    "sector": "Basic Industries",
    "mktcap": "Small",
    "bb_window": null,
    "bb_std": null,
    "peers": "$TECK $IVN.TO $TRQ.TO $SPY",
    "ror": 11.34,
    "entry_frequency": 12,
    "200sma_double_agent": 2
  },
  {
    "ticker": "BXRX",
    "sector": "Health Care",
    "mktcap": "Small",
    "bb_window": null,
    "bb_std": null,
    "peers": "$JNJ $PFE $MRK $SPY",
    "ror": 11.29,
    "entry_frequency": 12,
    "200sma_double_agent": 2
  },
  {
    "ticker": "EXTN",
    "sector": "Technology",
    "mktcap": "Small",
    "bb_window": null,
    "bb_std": null,
    "peers": "$SLB $BKR $HAL $SPY",
    "ror": 10.0,
    "entry_frequency": 11,
    "200sma_double_agent": 2
  },
  {
    "ticker": "NVCN",
    "sector": "Health Care",
    "mktcap": "Small",
    "bb_window": null,
    "bb_std": null,
    "peers": "$PRN.TO $OPS.TO $TMD.TO $SPY",
    "ror": 9.67,
    "entry_frequency": 11,
    "200sma_double_agent": 2
  },
  {
    "ticker": "CALA",
    "sector": "Health Care",
    "mktcap": "Small",
    "bb_window": null,
    "bb_std": null,
    "peers": "$950160.KQ $ABBV $AMGN $SPY",
    "ror": 9.58,
    "entry_frequency": 11,
    "200sma_double_agent": 2
  },
  {
    "ticker": "IMRA",
    "sector": "Health Care",
    "mktcap": "Small",
    "bb_window": null,
    "bb_std": null,
    "peers": "$JNJ $PFE $MRK $SPY",
    "ror": 9.07,
    "entry_frequency": 10,
    "200sma_double_agent": 2
  },
  {
    "ticker": "PUYI",
    "sector": "Finance",
    "mktcap": "Small",
    "bb_window": null,
    "bb_std": null,
    "peers": "$1359.HK $2799.HK $000563.SZ $SPY",
    "ror": 8.96,
    "entry_frequency": 10,
    "200sma_double_agent": 2
  },
  {
    "ticker": "CDTX",
    "sector": "Health Care",
    "mktcap": "Small",
    "bb_window": null,
    "bb_std": null,
    "peers": "$950160.KQ $ABBV $AMGN $SPY",
    "ror": 8.79,
    "entry_frequency": 10,
    "200sma_double_agent": 2
  },
  {
    "ticker": "OSMT",
    "sector": "Health Care",
    "mktcap": "Small",
    "bb_window": null,
    "bb_std": null,
    "peers": "$JNJ $PFE $MRK $SPY",
    "ror": 8.1,
    "entry_frequency": 9,
    "200sma_double_agent": 2
  },
  {
    "ticker": "ADMA",
    "sector": "Health Care",
    "mktcap": "Small",
    "bb_window": null,
    "bb_std": null,
    "peers": "$950160.KQ $ABBV $AMGN $SPY",
    "ror": 7.77,
    "entry_frequency": 9,
    "200sma_double_agent": 2
  },
  {
    "ticker": "CFRX",
    "sector": "Health Care",
    "mktcap": "Small",
    "bb_window": null,
    "bb_std": null,
    "peers": "$950160.KQ $ABBV $AMGN $SPY",
    "ror": 7.42,
    "entry_frequency": 8,
    "200sma_double_agent": 2
  },
  {
    "ticker": "RKDA",
    "sector": "Consumer Non-Durables",
    "mktcap": "Small",
    "bb_window": null,
    "bb_std": null,
    "peers": "$ADM $DAR $BG $SPY",
    "ror": 7.41,
    "entry_frequency": 8,
    "200sma_double_agent": 2
  },
  {
    "ticker": "GSV",
    "sector": "Basic Industries",
    "mktcap": "Small",
    "bb_window": null,
    "bb_std": null,
    "peers": "$ABX.TO $FNV.TO $WPM.TO $SPY",
    "ror": 7.41,
    "entry_frequency": 8,
    "200sma_double_agent": 2
  },
  {
    "ticker": "PSTI",
    "sector": "Health Care",
    "mktcap": "Small",
    "bb_window": null,
    "bb_std": null,
    "peers": "$BONS.TA $KMDA.TA $EVGN.TA $SPY",
    "ror": 7.14,
    "entry_frequency": 8,
    "200sma_double_agent": 2
  },
  {
    "ticker": "MKD",
    "sector": "Miscellaneous",
    "mktcap": "Small",
    "bb_window": null,
    "bb_std": null,
    "peers": "$3690.HK $9618.HK $BABA $SPY",
    "ror": 6.73,
    "entry_frequency": 8,
    "200sma_double_agent": 2
  },
  {
    "ticker": "AQST",
    "sector": "Health Care",
    "mktcap": "Small",
    "bb_window": null,
    "bb_std": null,
    "peers": "$JNJ $PFE $MRK $SPY",
    "ror": 6.6,
    "entry_frequency": 8,
    "200sma_double_agent": 2
  },
  {
    "ticker": "GLOP",
    "sector": "Consumer Services",
    "mktcap": "Small",
    "bb_window": null,
    "bb_std": null,
    "peers": "$OET.OL $GLOG $TNP $SPY",
    "ror": 6.36,
    "entry_frequency": 7,
    "200sma_double_agent": 2
  },
  {
    "ticker": "REDU",
    "sector": "Consumer Services",
    "mktcap": "Small",
    "bb_window": null,
    "bb_std": null,
    "peers": "$002607.SZ $667.HK $TAL $SPY",
    "ror": 6.34,
    "entry_frequency": 7,
    "200sma_double_agent": 2
  },
  {
    "ticker": "KRMD",
    "sector": "Health Care",
    "mktcap": "Small",
    "bb_window": null,
    "bb_std": null,
    "peers": "$ABT $DHR $SYK $SPY",
    "ror": 5.52,
    "entry_frequency": 7,
    "200sma_double_agent": 2
  },
  {
    "ticker": "HEPA",
    "sector": "Health Care",
    "mktcap": "Small",
    "bb_window": null,
    "bb_std": null,
    "peers": "$JNJ $PFE $MRK $SPY",
    "ror": 5.46,
    "entry_frequency": 6,
    "200sma_double_agent": 2
  },
  {
    "ticker": "NRBO",
    "sector": "Health Care",
    "mktcap": "Small",
    "bb_window": null,
    "bb_std": null,
    "peers": "$950160.KQ $ABBV $AMGN $SPY",
    "ror": 5.24,
    "entry_frequency": 6,
    "200sma_double_agent": 2
  },
  {
    "ticker": "NEPT",
    "sector": "Health Care",
    "mktcap": "Small",
    "bb_window": null,
    "bb_std": null,
    "peers": "$JWEL.TO $TAAT.CN $AHC.TO $SPY",
    "ror": 5.19,
    "entry_frequency": 6,
    "200sma_double_agent": 2
  },
  {
    "ticker": "WTER",
    "sector": "Consumer Non-Durables",
    "mktcap": "Small",
    "bb_window": null,
    "bb_std": null,
    "peers": "$KO $PEP $KDP $SPY",
    "ror": 5.12,
    "entry_frequency": 6,
    "200sma_double_agent": 2
  },
  {
    "ticker": "HYMC",
    "sector": "Basic Industries",
    "mktcap": "Small",
    "bb_window": null,
    "bb_std": null,
    "peers": "$NEM $RGLD $CDE $SPY",
    "ror": 5.12,
    "entry_frequency": 6,
    "200sma_double_agent": 2
  },
  {
    "ticker": "LUMO",
    "sector": "Health Care",
    "mktcap": "Small",
    "bb_window": null,
    "bb_std": null,
    "peers": "$950160.KQ $ABBV $AMGN $SPY",
    "ror": 4.81,
    "entry_frequency": 6,
    "200sma_double_agent": 2
  },
  {
    "ticker": "TRVN",
    "sector": "Health Care",
    "mktcap": "Small",
    "bb_window": null,
    "bb_std": null,
    "peers": "$950160.KQ $ABBV $AMGN $SPY",
    "ror": 4.74,
    "entry_frequency": 6,
    "200sma_double_agent": 2
  },
  {
    "ticker": "ASPU",
    "sector": "Consumer Services",
    "mktcap": "Small",
    "bb_window": null,
    "bb_std": null,
    "peers": "$CHGG $BFAM $LOPE $SPY",
    "ror": 4.63,
    "entry_frequency": 6,
    "200sma_double_agent": 2
  },
  {
    "ticker": "SUPV",
    "sector": "Finance",
    "mktcap": "Small",
    "bb_window": null,
    "bb_std": null,
    "peers": "$SPY $DIA $IWM $QQQ",
    "ror": 4.49,
    "entry_frequency": 5,
    "200sma_double_agent": 2
  },
  {
    "ticker": "AGRX",
    "sector": "Health Care",
    "mktcap": "Small",
    "bb_window": null,
    "bb_std": null,
    "peers": "$JNJ $PFE $MRK $SPY",
    "ror": 4.04,
    "entry_frequency": 5,
    "200sma_double_agent": 2
  },
  {
    "ticker": "FTK",
    "sector": "Basic Industries",
    "mktcap": "Small",
    "bb_window": null,
    "bb_std": null,
    "peers": "$SHW $ECL $DD $SPY",
    "ror": 3.77,
    "entry_frequency": 5,
    "200sma_double_agent": 2
  },
  {
    "ticker": "BSGM",
    "sector": "Health Care",
    "mktcap": "Small",
    "bb_window": null,
    "bb_std": null,
    "peers": "$ABT $DHR $SYK $SPY",
    "ror": 3.58,
    "entry_frequency": 5,
    "200sma_double_agent": 2
  },
  {
    "ticker": "LMPX",
    "sector": "Consumer Durables",
    "mktcap": "Small",
    "bb_window": null,
    "bb_std": null,
    "peers": "$CVNA $ORLY $AZO $SPY",
    "ror": 3.35,
    "entry_frequency": 4,
    "200sma_double_agent": 4
  },
  {
    "ticker": "GLMD",
    "sector": "Health Care",
    "mktcap": "Small",
    "bb_window": null,
    "bb_std": null,
    "peers": "$BONS.TA $KMDA.TA $EVGN.TA $SPY",
    "ror": 3.0,
    "entry_frequency": 4,
    "200sma_double_agent": 4
  },
  {
    "ticker": "CHMA",
    "sector": "Health Care",
    "mktcap": "Small",
    "bb_window": null,
    "bb_std": null,
    "peers": "$JNJ $PFE $MRK $SPY",
    "ror": 2.99,
    "entry_frequency": 4,
    "200sma_double_agent": 3
  },
  {
    "ticker": "TRX",
    "sector": "Basic Industries",
    "mktcap": "Small",
    "bb_window": null,
    "bb_std": null,
    "peers": "$ABX.TO $FNV.TO $WPM.TO $SPY",
    "ror": 2.62,
    "entry_frequency": 4,
    "200sma_double_agent": 4
  },
  {
    "ticker": "VYGR",
    "sector": "Health Care",
    "mktcap": "Small",
    "bb_window": null,
    "bb_std": null,
    "peers": "$950160.KQ $ABBV $AMGN $SPY",
    "ror": 2.53,
    "entry_frequency": 4,
    "200sma_double_agent": 4
  },
  {
    "ticker": "FONR",
    "sector": "Health Care",
    "mktcap": "Small",
    "bb_window": null,
    "bb_std": null,
    "peers": "$ABT $DHR $SYK $SPY",
    "ror": 2.45,
    "entry_frequency": 3,
    "200sma_double_agent": 5
  },
  {
    "ticker": "PAYS",
    "sector": "Miscellaneous",
    "mktcap": "Small",
    "bb_window": null,
    "bb_std": null,
    "peers": "$V $MA $PYPL $SPY",
    "ror": 2.36,
    "entry_frequency": 3,
    "200sma_double_agent": 4
  },
  {
    "ticker": "MMAC",
    "sector": "Finance",
    "mktcap": "Small",
    "bb_window": null,
    "bb_std": null,
    "peers": "$RKT $PCSO $UWMC $SPY",
    "ror": 2.17,
    "entry_frequency": 3,
    "200sma_double_agent": 4
  },
  {
    "ticker": "KMDA",
    "sector": "Health Care",
    "mktcap": "Small",
    "bb_window": null,
    "bb_std": null,
    "peers": "$BONS.TA $KMDA.TA $EVGN.TA $SPY",
    "ror": 2.11,
    "entry_frequency": 3,
    "200sma_double_agent": 4
  },
  {
    "ticker": "GNE",
    "sector": "Public Utilities",
    "mktcap": "Small",
    "bb_window": null,
    "bb_std": null,
    "peers": "$NEE $DUK $SO $SPY",
    "ror": 1.69,
    "entry_frequency": 3,
    "200sma_double_agent": 7
  },
  {
    "ticker": "FENC",
    "sector": "Health Care",
    "mktcap": "Small",
    "bb_window": null,
    "bb_std": null,
    "peers": "$950160.KQ $ABBV $AMGN $SPY",
    "ror": 1.4,
    "entry_frequency": 2,
    "200sma_double_agent": 15
  },
  {
    "ticker": "CYCN",
    "sector": "Health Care",
    "mktcap": "Small",
    "bb_window": null,
    "bb_std": null,
    "peers": "$950160.KQ $ABBV $AMGN $SPY",
    "ror": 1.4,
    "entry_frequency": 2,
    "200sma_double_agent": 5
  },
  {
    "ticker": "ELMD",
    "sector": "Health Care",
    "mktcap": "Small",
    "bb_window": null,
    "bb_std": null,
    "peers": "$ABT $DHR $SYK $SPY",
    "ror": 1.18,
    "entry_frequency": 2,
    "200sma_double_agent": 8
  },
  {
    "ticker": "NSH",
    "sector": "Finance",
    "mktcap": "Small",
    "bb_window": null,
    "bb_std": null,
    "peers": "$SPY $DIA $IWM $QQQ",
    "ror": 0.95,
    "entry_frequency": 2,
    "200sma_double_agent": 6
  },
  {
    "ticker": "COFS",
    "sector": "Finance",
    "mktcap": "Small",
    "bb_window": null,
    "bb_std": null,
    "peers": "$TFC $PNC $FRC $SPY",
    "ror": 0.76,
    "entry_frequency": 2,
    "200sma_double_agent": 9
  },
  {
    "ticker": "ALCO",
    "sector": "Consumer Non-Durables",
    "mktcap": "Small",
    "bb_window": null,
    "bb_std": null,
    "peers": "$ADM $DAR $BG $SPY",
    "ror": 0.69,
    "entry_frequency": 2,
    "200sma_double_agent": 8
  },
  {
    "ticker": "FNHC",
    "sector": "Finance",
    "mktcap": "Small",
    "bb_window": null,
    "bb_std": null,
    "peers": "$PGR $TRV $ALL $SPY",
    "ror": 0.64,
    "entry_frequency": 2,
    "200sma_double_agent": 20
  },
  {
    "ticker": "ARDS",
    "sector": "Health Care",
    "mktcap": "Small",
    "bb_window": null,
    "bb_std": null,
    "peers": "$950160.KQ $ABBV $AMGN $SPY",
    "ror": 0.44,
    "entry_frequency": 1,
    "200sma_double_agent": 9
  },
  {
    "ticker": "OTIC",
    "sector": "Health Care",
    "mktcap": "Small",
    "bb_window": null,
    "bb_std": null,
    "peers": "$JNJ $PFE $MRK $SPY",
    "ror": 0.23,
    "entry_frequency": 1,
    "200sma_double_agent": 7
  },
  {
    "ticker": "APT",
    "sector": "Health Care",
    "mktcap": "Small",
    "bb_window": null,
    "bb_std": null,
    "peers": "$DRT.TO $PFB.TO $APT $SPY",
    "ror": 0.1,
    "entry_frequency": 1,
    "200sma_double_agent": 15
  },
  {
    "ticker": "MOGU",
    "sector": "Miscellaneous",
    "mktcap": "Small",
    "bb_window": null,
    "bb_std": null,
    "peers": "$3690.HK $9618.HK $BABA $SPY",
    "ror": -0.0,
    "entry_frequency": 1,
    "200sma_double_agent": 32
  },
  {
    "ticker": "AVCO",
    "sector": "Consumer Services",
    "mktcap": "Small",
    "bb_window": null,
    "bb_std": null,
    "peers": "$CVS $CI $LH $SPY",
    "ror": -0.0,
    "entry_frequency": 1,
    "200sma_double_agent": 7
  },
  {
    "ticker": "RGCO",
    "sector": "Public Utilities",
    "mktcap": "Small",
    "bb_window": null,
    "bb_std": null,
    "peers": "$ATO $UGI $NFG $SPY",
    "ror": -0.41,
    "entry_frequency": 1,
    "200sma_double_agent": 19
  },
  {
    "ticker": "TELA",
    "sector": "Health Care",
    "mktcap": "Small",
    "bb_window": null,
    "bb_std": null,
    "peers": "$950130.KQ $ALGN $WST $SPY",
    "ror": -0.51,
    "entry_frequency": 1,
    "200sma_double_agent": 16
  },
  {
    "ticker": "SCPH",
    "sector": "Health Care",
    "mktcap": "Small",
    "bb_window": null,
    "bb_std": null,
    "peers": "$JNJ $PFE $MRK $SPY",
    "ror": -0.61,
    "entry_frequency": 1,
    "200sma_double_agent": 19
  },
  {
    "ticker": "OPTN",
    "sector": "Health Care",
    "mktcap": "Small",
    "bb_window": null,
    "bb_std": null,
    "peers": "$JNJ $PFE $MRK $SPY",
    "ror": -0.85,
    "entry_frequency": 1,
    "200sma_double_agent": 18
  },
  {
    "ticker": "CODX",
    "sector": "Health Care",
    "mktcap": "Small",
    "bb_window": null,
    "bb_std": null,
    "peers": "$ABT $DHR $SYK $SPY",
    "ror": -1.0,
    "entry_frequency": 1,
    "200sma_double_agent": 15
  },
  {
    "ticker": "CNCE",
    "sector": "Health Care",
    "mktcap": "Small",
    "bb_window": null,
    "bb_std": null,
    "peers": "$950160.KQ $ABBV $AMGN $SPY",
    "ror": -1.3,
    "entry_frequency": 1,
    "200sma_double_agent": 9
  },
  {
    "ticker": "CMCL",
    "sector": "Basic Industries",
    "mktcap": "Small",
    "bb_window": null,
    "bb_std": null,
    "peers": "$CEY.L $CMCL $RYR.V $SPY",
    "ror": -1.58,
    "entry_frequency": 1,
    "200sma_double_agent": 20
  },
  {
    "ticker": "GTT",
    "sector": "Public Utilities",
    "mktcap": "Small",
    "bb_window": null,
    "bb_std": null,
    "peers": "$SNOW $TWLO $OKTA $SPY",
    "ror": -1.67,
    "entry_frequency": 1,
    "200sma_double_agent": 18
  },
  {
    "ticker": "CABA",
    "sector": "Health Care",
    "mktcap": "Small",
    "bb_window": null,
    "bb_std": null,
    "peers": "$950160.KQ $ABBV $AMGN $SPY",
    "ror": -2.23,
    "entry_frequency": 1,
    "200sma_double_agent": 20
  },
  {
    "ticker": "CXDC",
    "sector": "Capital Goods",
    "mktcap": "Small",
    "bb_window": null,
    "bb_std": null,
    "peers": "$1316.HK $QS $BWA $SPY",
    "ror": -2.39,
    "entry_frequency": 1,
    "200sma_double_agent": 5
  },
  {
    "ticker": "WVE",
    "sector": "Health Care",
    "mktcap": "Small",
    "bb_window": null,
    "bb_std": null,
    "peers": "$H02.SI $WVE $42C.SI $SPY",
    "ror": -2.55,
    "entry_frequency": 1,
    "200sma_double_agent": 15
  },
  {
    "ticker": "LQDA",
    "sector": "Health Care",
    "mktcap": "Small",
    "bb_window": null,
    "bb_std": null,
    "peers": "$JNJ $PFE $MRK $SPY",
    "ror": -2.77,
    "entry_frequency": 1,
    "200sma_double_agent": 7
  },
  {
    "ticker": "LMNL",
    "sector": "Health Care",
    "mktcap": "Small",
    "bb_window": null,
    "bb_std": null,
    "peers": "$AUP.TO $ZYME $TRIL.TO $SPY",
    "ror": -4.84,
    "entry_frequency": 1,
    "200sma_double_agent": 37
  },
  {
    "ticker": "TARA",
    "sector": "Health Care",
    "mktcap": "Small",
    "bb_window": null,
    "bb_std": null,
    "peers": "$950160.KQ $ABBV $AMGN $SPY",
    "ror": -8.53,
    "entry_frequency": 1,
    "200sma_double_agent": 40
  }
]