[
  {
    "ticker": "TPL",
    "sector": "Energy",
    "mktcap": "VeryLarge",
    "bb_window": 3,
    "bb_std": 0.1,
    "peers": "$COP $EOG $PXD $SPY",
    "ror": 89.41,
    "entry_frequency": 180
  },
  {
    "ticker": "UHAL",
    "sector": "Consumer Services",
    "mktcap": "VeryLarge",
    "bb_window": 3,
    "bb_std": 0.1,
    "peers": "$UBER $ODFL $LYFT $SPY",
    "ror": 31.4,
    "entry_frequency": 64
  },
  {
    "ticker": "HPE",
    "sector": "Technology",
    "mktcap": "VeryLarge",
    "bb_window": 3,
    "bb_std": 0.1,
    "peers": "$AAPL $DELL $HPQ $SPY",
    "ror": 28.48,
    "entry_frequency": 58
  },
  {
    "ticker": "SNA",
    "sector": "Capital Goods",
    "mktcap": "VeryLarge",
    "bb_window": 3,
    "bb_std": 0.1,
    "peers": "$ITW $PH $SWK $SPY",
    "ror": 26.87,
    "entry_frequency": 55
  },
  {
    "ticker": "DELL",
    "sector": "Technology",
    "mktcap": "VeryLarge",
    "bb_window": 3,
    "bb_std": 0.1,
    "peers": "$AAPL $DELL $HPQ $SPY",
    "ror": 20.74,
    "entry_frequency": 42
  },
  {
    "ticker": "TROW",
    "sector": "Finance",
    "mktcap": "VeryLarge",
    "bb_window": 3,
    "bb_std": 0.5,
    "peers": "$BLK $BX $KKR $SPY",
    "ror": 12.33,
    "entry_frequency": 26
  },
  {
    "ticker": "WU",
    "sector": "Miscellaneous",
    "mktcap": "VeryLarge",
    "bb_window": 3,
    "bb_std": 0.1,
    "peers": "$V $MA $PYPL $SPY",
    "ror": 10.49,
    "entry_frequency": 22
  }
]