[
  {
    "ticker": "ORGO",
    "sector": "Health Care",
    "mktcap": "Large",
    "bb_window": null,
    "bb_std": null,
    "peers": "$950160.KQ $ABBV $AMGN $SPY",
    "ror": 45.79,
    "entry_frequency": 93,
    "200sma_double_agent": 2
  },
  {
    "ticker": "AYI",
    "sector": "Consumer Durables",
    "mktcap": "Large",
    "bb_window": null,
    "bb_std": null,
    "peers": "$EMR $3665.TW $ROK $SPY",
    "ror": 32.35,
    "entry_frequency": 66,
    "200sma_double_agent": 2
  },
  {
    "ticker": "LOB",
    "sector": "Finance",
    "mktcap": "Large",
    "bb_window": null,
    "bb_std": null,
    "peers": "$TFC $PNC $FRC $SPY",
    "ror": 31.34,
    "entry_frequency": 64,
    "200sma_double_agent": 2
  },
  {
    "ticker": "UFPI",
    "sector": "Basic Industries",
    "mktcap": "Large",
    "bb_window": null,
    "bb_std": null,
    "peers": "$CARR $MAS $FBHS $SPY",
    "ror": 28.43,
    "entry_frequency": 58,
    "200sma_double_agent": 2
  },
  {
    "ticker": "LPX",
    "sector": "Basic Industries",
    "mktcap": "Large",
    "bb_window": null,
    "bb_std": null,
    "peers": "$LPX $RRIF $KEWL $SPY",
    "ror": 27.58,
    "entry_frequency": 56,
    "200sma_double_agent": 2
  },
  {
    "ticker": "OLN",
    "sector": "Basic Industries",
    "mktcap": "Large",
    "bb_window": null,
    "bb_std": null,
    "peers": "$DOW $WLK $OLN $SPY",
    "ror": 24.22,
    "entry_frequency": 49,
    "200sma_double_agent": 2
  },
  {
    "ticker": "SGRY",
    "sector": "Health Care",
    "mktcap": "Large",
    "bb_window": null,
    "bb_std": null,
    "peers": "$HCA $UHS $EHC $SPY",
    "ror": 20.56,
    "entry_frequency": 42,
    "200sma_double_agent": 2
  },
  {
    "ticker": "FLR",
    "sector": "Basic Industries",
    "mktcap": "Large",
    "bb_window": null,
    "bb_std": null,
    "peers": "$PWR $ACM $MTZ $SPY",
    "ror": 19.82,
    "entry_frequency": 41,
    "200sma_double_agent": 2
  },
  {
    "ticker": "CXP",
    "sector": "Consumer Services",
    "mktcap": "Large",
    "bb_window": null,
    "bb_std": null,
    "peers": "$ARE $BXP $VNO $SPY",
    "ror": 19.29,
    "entry_frequency": 40,
    "200sma_double_agent": 2
  },
  {
    "ticker": "STAY",
    "sector": "Consumer Services",
    "mktcap": "Large",
    "bb_window": null,
    "bb_std": null,
    "peers": "$ABNB $MAR $HLT $SPY",
    "ror": 18.92,
    "entry_frequency": 39,
    "200sma_double_agent": 2
  },
  {
    "ticker": "CAR",
    "sector": "Consumer Services",
    "mktcap": "Large",
    "bb_window": null,
    "bb_std": null,
    "peers": "$UBER $ODFL $LYFT $SPY",
    "ror": 18.74,
    "entry_frequency": 38,
    "200sma_double_agent": 2
  },
  {
    "ticker": "SLM",
    "sector": "Finance",
    "mktcap": "Large",
    "bb_window": null,
    "bb_std": null,
    "peers": "$AXP $COF $DFS $SPY",
    "ror": 18.7,
    "entry_frequency": 38,
    "200sma_double_agent": 2
  },
  {
    "ticker": "BOX",
    "sector": "Technology",
    "mktcap": "Large",
    "bb_window": null,
    "bb_std": null,
    "peers": "$ADBE $CRM $INTU $SPY",
    "ror": 18.57,
    "entry_frequency": 38,
    "200sma_double_agent": 2
  },
  {
    "ticker": "TX",
    "sector": "Basic Industries",
    "mktcap": "Large",
    "bb_window": null,
    "bb_std": null,
    "peers": "$MT.AS $TX $APAM.AS $SPY",
    "ror": 17.18,
    "entry_frequency": 35,
    "200sma_double_agent": 2
  },
  {
    "ticker": "SMCI",
    "sector": "Technology",
    "mktcap": "Large",
    "bb_window": null,
    "bb_std": null,
    "peers": "$AAPL $DELL $HPQ $SPY",
    "ror": 16.1,
    "entry_frequency": 33,
    "200sma_double_agent": 2
  },
  {
    "ticker": "SKX",
    "sector": "Consumer Non-Durables",
    "mktcap": "Large",
    "bb_window": null,
    "bb_std": null,
    "peers": "$NKE $DECK $SKX $SPY",
    "ror": 16.01,
    "entry_frequency": 33,
    "200sma_double_agent": 2
  },
  {
    "ticker": "OMI",
    "sector": "Health Care",
    "mktcap": "Large",
    "bb_window": null,
    "bb_std": null,
    "peers": "$MCK $ABC $CAH $SPY",
    "ror": 15.94,
    "entry_frequency": 33,
    "200sma_double_agent": 2
  },
  {
    "ticker": "SAIA",
    "sector": "Transportation",
    "mktcap": "Large",
    "bb_window": null,
    "bb_std": null,
    "peers": "$UBER $ODFL $LYFT $SPY",
    "ror": 15.09,
    "entry_frequency": 31,
    "200sma_double_agent": 2
  },
  {
    "ticker": "JACK",
    "sector": "Consumer Services",
    "mktcap": "Large",
    "bb_window": null,
    "bb_std": null,
    "peers": "$MCD $SBUX $CMG $SPY",
    "ror": 14.55,
    "entry_frequency": 30,
    "200sma_double_agent": 2
  },
  {
    "ticker": "ABG",
    "sector": "Consumer Durables",
    "mktcap": "Large",
    "bb_window": null,
    "bb_std": null,
    "peers": "$CVNA $ORLY $AZO $SPY",
    "ror": 13.86,
    "entry_frequency": 29,
    "200sma_double_agent": 2
  },
  {
    "ticker": "ORI",
    "sector": "Finance",
    "mktcap": "Large",
    "bb_window": null,
    "bb_std": null,
    "peers": "$PGR $TRV $ALL $SPY",
    "ror": 13.55,
    "entry_frequency": 28,
    "200sma_double_agent": 2
  },
  {
    "ticker": "BWXT",
    "sector": "Energy",
    "mktcap": "Large",
    "bb_window": null,
    "bb_std": null,
    "peers": "$BA $RTX $LMT $SPY",
    "ror": 13.51,
    "entry_frequency": 28,
    "200sma_double_agent": 2
  },
  {
    "ticker": "NAVI",
    "sector": "Finance",
    "mktcap": "Large",
    "bb_window": null,
    "bb_std": null,
    "peers": "$AXP $COF $DFS $SPY",
    "ror": 13.36,
    "entry_frequency": 28,
    "200sma_double_agent": 2
  },
  {
    "ticker": "HRB",
    "sector": "Consumer Services",
    "mktcap": "Large",
    "bb_window": null,
    "bb_std": null,
    "peers": "$SCI $TMX $FTDR $SPY",
    "ror": 13.26,
    "entry_frequency": 28,
    "200sma_double_agent": 2
  },
  {
    "ticker": "ACM",
    "sector": "Consumer Services",
    "mktcap": "Large",
    "bb_window": null,
    "bb_std": null,
    "peers": "$PWR $ACM $MTZ $SPY",
    "ror": 13.2,
    "entry_frequency": 27,
    "200sma_double_agent": 2
  },
  {
    "ticker": "POR",
    "sector": "Public Utilities",
    "mktcap": "Large",
    "bb_window": null,
    "bb_std": null,
    "peers": "$NEE $DUK $SO $SPY",
    "ror": 12.97,
    "entry_frequency": 27,
    "200sma_double_agent": 2
  },
  {
    "ticker": "DDS",
    "sector": "Consumer Services",
    "mktcap": "Large",
    "bb_window": null,
    "bb_std": null,
    "peers": "$KSS $JWN $M $SPY",
    "ror": 12.55,
    "entry_frequency": 26,
    "200sma_double_agent": 2
  },
  {
    "ticker": "SFBS",
    "sector": "Finance",
    "mktcap": "Large",
    "bb_window": null,
    "bb_std": null,
    "peers": "$TFC $PNC $FRC $SPY",
    "ror": 12.46,
    "entry_frequency": 26,
    "200sma_double_agent": 2
  },
  {
    "ticker": "ABM",
    "sector": "Finance",
    "mktcap": "Large",
    "bb_window": null,
    "bb_std": null,
    "peers": "$WM $RSG $ROL $SPY",
    "ror": 12.34,
    "entry_frequency": 26,
    "200sma_double_agent": 2
  },
  {
    "ticker": "IHRT",
    "sector": "Consumer Services",
    "mktcap": "Large",
    "bb_window": null,
    "bb_std": null,
    "peers": "$VIAC $FOXA $DISCA $SPY",
    "ror": 12.25,
    "entry_frequency": 26,
    "200sma_double_agent": 2
  },
  {
    "ticker": "HII",
    "sector": "Capital Goods",
    "mktcap": "Large",
    "bb_window": null,
    "bb_std": null,
    "peers": "$BA $RTX $LMT $SPY",
    "ror": 11.82,
    "entry_frequency": 25,
    "200sma_double_agent": 2
  },
  {
    "ticker": "AVA",
    "sector": "Public Utilities",
    "mktcap": "Large",
    "bb_window": null,
    "bb_std": null,
    "peers": "$D $SRE $PEG $SPY",
    "ror": 11.21,
    "entry_frequency": 23,
    "200sma_double_agent": 3
  },
  {
    "ticker": "THG",
    "sector": "Finance",
    "mktcap": "Large",
    "bb_window": null,
    "bb_std": null,
    "peers": "$PGR $TRV $ALL $SPY",
    "ror": 10.48,
    "entry_frequency": 22,
    "200sma_double_agent": 3
  },
  {
    "ticker": "MMS",
    "sector": "Miscellaneous",
    "mktcap": "Large",
    "bb_window": null,
    "bb_std": null,
    "peers": "$V $MA $PYPL $SPY",
    "ror": 10.45,
    "entry_frequency": 22,
    "200sma_double_agent": 3
  },
  {
    "ticker": "FIX",
    "sector": "Capital Goods",
    "mktcap": "Large",
    "bb_window": null,
    "bb_std": null,
    "peers": "$PWR $ACM $MTZ $SPY",
    "ror": 10.4,
    "entry_frequency": 22,
    "200sma_double_agent": 3
  },
  {
    "ticker": "WH",
    "sector": "Consumer Services",
    "mktcap": "Large",
    "bb_window": null,
    "bb_std": null,
    "peers": "$ABNB $MAR $HLT $SPY",
    "ror": 10.39,
    "entry_frequency": 22,
    "200sma_double_agent": 3
  },
  {
    "ticker": "FUL",
    "sector": "Basic Industries",
    "mktcap": "Large",
    "bb_window": null,
    "bb_std": null,
    "peers": "$SHW $ECL $DD $SPY",
    "ror": 10.09,
    "entry_frequency": 21,
    "200sma_double_agent": 3
  },
  {
    "ticker": "CNMD",
    "sector": "Health Care",
    "mktcap": "Large",
    "bb_window": null,
    "bb_std": null,
    "peers": "$ABT $DHR $SYK $SPY",
    "ror": 9.93,
    "entry_frequency": 21,
    "200sma_double_agent": 3
  },
  {
    "ticker": "KNX",
    "sector": "Transportation",
    "mktcap": "Large",
    "bb_window": null,
    "bb_std": null,
    "peers": "$UBER $ODFL $LYFT $SPY",
    "ror": 9.86,
    "entry_frequency": 21,
    "200sma_double_agent": 4
  },
  {
    "ticker": "RS",
    "sector": "Basic Industries",
    "mktcap": "Large",
    "bb_window": null,
    "bb_std": null,
    "peers": "$NUE $STLD $RS $SPY",
    "ror": 9.7,
    "entry_frequency": 20,
    "200sma_double_agent": 4
  },
  {
    "ticker": "EXP",
    "sector": "Capital Goods",
    "mktcap": "Large",
    "bb_window": null,
    "bb_std": null,
    "peers": "$VMC $MLM $EXP $SPY",
    "ror": 9.22,
    "entry_frequency": 19,
    "200sma_double_agent": 4
  },
  {
    "ticker": "SANM",
    "sector": "Technology",
    "mktcap": "Large",
    "bb_window": null,
    "bb_std": null,
    "peers": "$IPGP $JBL $SANM $SPY",
    "ror": 9.05,
    "entry_frequency": 19,
    "200sma_double_agent": 5
  },
  {
    "ticker": "NSA",
    "sector": "Consumer Services",
    "mktcap": "Large",
    "bb_window": null,
    "bb_std": null,
    "peers": "$AMT $CCI $EQIX $SPY",
    "ror": 8.78,
    "entry_frequency": 19,
    "200sma_double_agent": 5
  },
  {
    "ticker": "ARES",
    "sector": "Finance",
    "mktcap": "Large",
    "bb_window": null,
    "bb_std": null,
    "peers": "$BLK $BX $KKR $SPY",
    "ror": 8.64,
    "entry_frequency": 18,
    "200sma_double_agent": 4
  },
  {
    "ticker": "NWE",
    "sector": "Public Utilities",
    "mktcap": "Large",
    "bb_window": null,
    "bb_std": null,
    "peers": "$D $SRE $PEG $SPY",
    "ror": 8.6,
    "entry_frequency": 18,
    "200sma_double_agent": 5
  },
  {
    "ticker": "CUBE",
    "sector": "Consumer Services",
    "mktcap": "Large",
    "bb_window": null,
    "bb_std": null,
    "peers": "$AMT $CCI $EQIX $SPY",
    "ror": 8.42,
    "entry_frequency": 18,
    "200sma_double_agent": 4
  },
  {
    "ticker": "CUB",
    "sector": "Capital Goods",
    "mktcap": "Large",
    "bb_window": null,
    "bb_std": null,
    "peers": "$BA $RTX $LMT $SPY",
    "ror": 8.26,
    "entry_frequency": 18,
    "200sma_double_agent": 5
  },
  {
    "ticker": "SASR",
    "sector": "Finance",
    "mktcap": "Large",
    "bb_window": null,
    "bb_std": null,
    "peers": "$TFC $PNC $FRC $SPY",
    "ror": 8.13,
    "entry_frequency": 17,
    "200sma_double_agent": 6
  },
  {
    "ticker": "STWD",
    "sector": "Consumer Services",
    "mktcap": "Large",
    "bb_window": null,
    "bb_std": null,
    "peers": "$NLY $AGNC $STWD $SPY",
    "ror": 8.11,
    "entry_frequency": 17,
    "200sma_double_agent": 6
  },
  {
    "ticker": "CIM",
    "sector": "Consumer Services",
    "mktcap": "Large",
    "bb_window": null,
    "bb_std": null,
    "peers": "$NLY $AGNC $STWD $SPY",
    "ror": 7.98,
    "entry_frequency": 17,
    "200sma_double_agent": 6
  },
  {
    "ticker": "STN",
    "sector": "Consumer Services",
    "mktcap": "Large",
    "bb_window": null,
    "bb_std": null,
    "peers": "$TRI.TO $STN.TO $IBG.TO $SPY",
    "ror": 7.78,
    "entry_frequency": 17,
    "200sma_double_agent": 4
  },
  {
    "ticker": "AA",
    "sector": "Basic Industries",
    "mktcap": "Large",
    "bb_window": null,
    "bb_std": null,
    "peers": "$AA $ARNC $KALU $SPY",
    "ror": 7.64,
    "entry_frequency": 16,
    "200sma_double_agent": 8
  },
  {
    "ticker": "PSB",
    "sector": "Consumer Services",
    "mktcap": "Large",
    "bb_window": null,
    "bb_std": null,
    "peers": "$WPC $VER $STOR $SPY",
    "ror": 7.49,
    "entry_frequency": 16,
    "200sma_double_agent": 5
  },
  {
    "ticker": "CSWI",
    "sector": "Basic Industries",
    "mktcap": "Large",
    "bb_window": null,
    "bb_std": null,
    "peers": "$CARR $MAS $FBHS $SPY",
    "ror": 7.3,
    "entry_frequency": 16,
    "200sma_double_agent": 7
  },
  {
    "ticker": "ADS",
    "sector": "Miscellaneous",
    "mktcap": "Large",
    "bb_window": null,
    "bb_std": null,
    "peers": "$V $MA $PYPL $SPY",
    "ror": 6.72,
    "entry_frequency": 14,
    "200sma_double_agent": 7
  },
  {
    "ticker": "KT",
    "sector": "Public Utilities",
    "mktcap": "Large",
    "bb_window": null,
    "bb_std": null,
    "peers": "$030200.KS $032640.KS $036630.KQ $SPY",
    "ror": 6.62,
    "entry_frequency": 14,
    "200sma_double_agent": 6
  },
  {
    "ticker": "NRZ",
    "sector": "Consumer Services",
    "mktcap": "Large",
    "bb_window": null,
    "bb_std": null,
    "peers": "$NLY $AGNC $STWD $SPY",
    "ror": 5.87,
    "entry_frequency": 13,
    "200sma_double_agent": 13
  },
  {
    "ticker": "MSM",
    "sector": "Capital Goods",
    "mktcap": "Large",
    "bb_window": null,
    "bb_std": null,
    "peers": "$FAST $URI $GWW $SPY",
    "ror": 5.46,
    "entry_frequency": 12,
    "200sma_double_agent": 11
  },
  {
    "ticker": "OSK",
    "sector": "Capital Goods",
    "mktcap": "Large",
    "bb_window": null,
    "bb_std": null,
    "peers": "$CAT $CMI $PCAR $SPY",
    "ror": 5.4,
    "entry_frequency": 12,
    "200sma_double_agent": 8
  },
  {
    "ticker": "CR",
    "sector": "Capital Goods",
    "mktcap": "Large",
    "bb_window": null,
    "bb_std": null,
    "peers": "$ITW $PH $SWK $SPY",
    "ror": 4.79,
    "entry_frequency": 11,
    "200sma_double_agent": 7
  },
  {
    "ticker": "PLXS",
    "sector": "Technology",
    "mktcap": "Large",
    "bb_window": null,
    "bb_std": null,
    "peers": "$IPGP $JBL $SANM $SPY",
    "ror": 4.76,
    "entry_frequency": 11,
    "200sma_double_agent": 10
  },
  {
    "ticker": "ITT",
    "sector": "Capital Goods",
    "mktcap": "Large",
    "bb_window": null,
    "bb_std": null,
    "peers": "$ITW $PH $SWK $SPY",
    "ror": 4.72,
    "entry_frequency": 10,
    "200sma_double_agent": 12
  },
  {
    "ticker": "CWST",
    "sector": "Public Utilities",
    "mktcap": "Large",
    "bb_window": null,
    "bb_std": null,
    "peers": "$WM $RSG $ROL $SPY",
    "ror": 4.59,
    "entry_frequency": 10,
    "200sma_double_agent": 16
  },
  {
    "ticker": "LSTR",
    "sector": "Transportation",
    "mktcap": "Large",
    "bb_window": null,
    "bb_std": null,
    "peers": "$UBER $ODFL $LYFT $SPY",
    "ror": 4.28,
    "entry_frequency": 10,
    "200sma_double_agent": 17
  },
  {
    "ticker": "UGI",
    "sector": "Public Utilities",
    "mktcap": "Large",
    "bb_window": null,
    "bb_std": null,
    "peers": "$ATO $UGI $NFG $SPY",
    "ror": 3.66,
    "entry_frequency": 8,
    "200sma_double_agent": 19
  },
  {
    "ticker": "MDU",
    "sector": "Basic Industries",
    "mktcap": "Large",
    "bb_window": null,
    "bb_std": null,
    "peers": "$D $SRE $PEG $SPY",
    "ror": 2.8,
    "entry_frequency": 7,
    "200sma_double_agent": 16
  },
  {
    "ticker": "SON",
    "sector": "Consumer Durables",
    "mktcap": "Large",
    "bb_window": null,
    "bb_std": null,
    "peers": "$IP $AVY $WRK $SPY",
    "ror": 2.8,
    "entry_frequency": 7,
    "200sma_double_agent": 20
  },
  {
    "ticker": "NFG",
    "sector": "Public Utilities",
    "mktcap": "Large",
    "bb_window": null,
    "bb_std": null,
    "peers": "$ATO $UGI $NFG $SPY",
    "ror": 1.98,
    "entry_frequency": 5,
    "200sma_double_agent": 19
  },
  {
    "ticker": "GWPH",
    "sector": "Health Care",
    "mktcap": "Large",
    "bb_window": null,
    "bb_std": null,
    "peers": "$AZN.L $GSK.L $GWPH $SPY",
    "ror": 1.19,
    "entry_frequency": 3,
    "200sma_double_agent": 17
  },
  {
    "ticker": "RP",
    "sector": "Technology",
    "mktcap": "Large",
    "bb_window": null,
    "bb_std": null,
    "peers": "$ADBE $CRM $INTU $SPY",
    "ror": 1.09,
    "entry_frequency": 3,
    "200sma_double_agent": 30
  },
  {
    "ticker": "MIK",
    "sector": "Consumer Services",
    "mktcap": "Large",
    "bb_window": null,
    "bb_std": null,
    "peers": "$TSCO $ULTA $FIVE $SPY",
    "ror": 0.73,
    "entry_frequency": 2,
    "200sma_double_agent": 21
  },
  {
    "ticker": "CNX",
    "sector": "Energy",
    "mktcap": "Large",
    "bb_window": null,
    "bb_std": null,
    "peers": "$COP $EOG $PXD $SPY",
    "ror": 0.5,
    "entry_frequency": 2,
    "200sma_double_agent": 54
  }
]