[
  {
    "ticker": "NMM",
    "sector": "Transportation",
    "mktcap": "Small",
    "bb_window": 6,
    "bb_std": 1.0,
    "peers": "$CMRE $NMCI $NMM $SPY",
    "ror": 152.09
  },
  {
    "ticker": "GTIM",
    "sector": "Consumer Services",
    "mktcap": "Small",
    "bb_window": 2,
    "bb_std": 0.8,
    "peers": "$MCD $SBUX $CMG $SPY",
    "ror": 114.74
  },
  {
    "ticker": "HQI",
    "sector": "Technology",
    "mktcap": "Small",
    "bb_window": 7,
    "bb_std": 1.0,
    "peers": "$RHI $UPWK $MAN $SPY",
    "ror": 87.79
  },
  {
    "ticker": "ESXB",
    "sector": "Finance",
    "mktcap": "Small",
    "bb_window": 7,
    "bb_std": 0.8,
    "peers": "$TFC $PNC $FRC $SPY",
    "ror": 27.36
  },
  {
    "ticker": "MNSB",
    "sector": "Finance",
    "mktcap": "Small",
    "bb_window": 7,
    "bb_std": 0.7,
    "peers": "$TFC $PNC $FRC $SPY",
    "ror": 25.52
  }
]